__init__.py
ddecoapiparser.py
ddecoapiparser-0.1.3.9.dist-info/METADATA
ddecoapiparser-0.1.3.9.dist-info/WHEEL
ddecoapiparser-0.1.3.9.dist-info/licenses/LICENSE
ddecoapiparser-0.1.3.9.dist-info/RECORD
