Metadata-Version: 2.4
Name: ddecoapiparser
Version: 0.1.3.9
Summary: Package to request and parse AquaDesk data via the DD-ECO-API
Project-URL: Homepage, https://github.com/AbelsWouter/ddecoapiparser
Project-URL: Bug Tracker, https://github.com/AbelsWouter/ddecoapiparser/issues
Author-email: Wouter Abels <wouter.abels@rws.nl>
License-File: LICENSE
Classifier: License :: OSI Approved :: MIT License
Classifier: Operating System :: OS Independent
Classifier: Programming Language :: Python :: 3
Requires-Python: >=3.7
Requires-Dist: numpy>=1.25.1
Requires-Dist: pandas>=2.0.3
Requires-Dist: requests>=2.31.0
